[{"page": 1, "chunk_index": 0, "text": "Prof. Dr. Muhammet ÖZEKES\nSORULAR - ŞEMALAR - ÖRNEKLERLE\nTEMEL HUKUK BİLGİSİ\n“Hukuka hâkim olan, hukuku hâkim kılan ve\nhukuku hâkim olan her şeye hâkim olur”\n12. Bası"}, {"page": 2, "chunk_index": 0, "text": "12. BASIYA ÖNSÖZ..........................................................................VII\n1. BASIYA ÖNSÖZ..............................................................................IX\nİÇİNDEKİLER................................................................................ XIII\nKONULARIN SİSTEMATİK PLANI............................................XXV\nSEÇİLMİŞ KAYNAKÇA............................................................ XXXIX\nKISALTMALAR.............................................................................. XLV\nGİRİŞ.....................................................................................................1\n1."}, {"page": 2, "chunk_index": 1, "text": "XLV\nGİRİŞ.....................................................................................................1\n1. Hukuk başlangıcı veya hukuka giriş derslerinin temel amacı\nnedir?...................................................................................................................1\n2. İyi bir hukukçu olmak için en baştan nelere dikkat etmek\ngerekir? İyi bir hukuk bilgisinin ve iyi bir hukukçu olmanın\ntemel formülü nedir?.......................................................................................2\n3. Hukuk başlangıcı dersinde nasıl bir yöntem izlenecektir? Hangi yöntemle bu dersi öğrenmek uygundur?......................................7\n§ 1. HUKUKUN EN TEMEL KAVRAMLARI (TEMEL\nHUKUK BILGISI IÇIN BAŞLANGIÇ).....................................11\n4."}, {"page": 2, "chunk_index": 2, "text": "HUKUKUN EN TEMEL KAVRAMLARI (TEMEL\nHUKUK BILGISI IÇIN BAŞLANGIÇ).....................................11\n4. “Hak” nedir?...................................................................................................11\n5. Hak sahipliği ve hakkın kullanılması genel olarak neyi ifade\netmektedir?......................................................................................................11\nİÇİNDEKİLER"}, {"page": 3, "chunk_index": 0, "text": "XIV\n6. Hakkın tanımı üzerinde ittifak edilmediği ve bu konuda tek\nbir bakış açısının olmadığı yukarıda belirtildi. Hak nasıl\naçıklanmaktadır, bu konudaki temel görüşler nelerdir?................... 12\n7. Hak ve ödev arasında nasıl bir ilişki vardır?.........................................14\n8. “Hukuk” nedir?..............................................................................................14\n9. Hukuk neyi gerçekleştirmeyi amaçlar?...................................................16\n10. Hukukun temeli ve kaynağı nedir?...........................................................18\n11. Hukukun tek bir anlamı mı vardır?.........................................................19\n12. Hukuki Pozitivizm ve Doğal Hukuk Karşıtlığından Ne\nAnlaşılması Gerekir?"}, {"page": 3, "chunk_index": 1, "text": "Hukuki Pozitivizm ve Doğal Hukuk Karşıtlığından Ne\nAnlaşılması Gerekir? Yaşayan Hukukta Bu Kuramların\nEtkileri Ne Şekilde Hissedilebilir?...........................................................20\n13. “Adalet” nedir?..............................................................................................24\n14. Adalet kavramı içinde neler yer almaktadır?....................................... 27\n15. Çok sık vurgulanan dağıtıcı ve denkleştirici adalet ne demektir?..29\n16. Eşitlik, aynı zamanda adaleti sağlar mı?.............................................. 31\n17. Hak, hukuk ve adalet arasında nasıl bir ilişki vardır?...................... 31\n§ 2. HAK KAVRAMI ILE İLGILI TEMEL BILGILER...................33\n18."}, {"page": 3, "chunk_index": 2, "text": "HAK KAVRAMI ILE İLGILI TEMEL BILGILER...................33\n18. Hakkın türleri genel olarak nelerdir?.....................................................33\n19. Kamu hakları ve özel haklar ayrımı hangi esasa\ndayanmaktadır?...........................................................................................33\n20. Kamu hakları kendi içinde hangi alt ayrımlara tâbidir?.................34\n21. Özel haklar kendi içinde hangi alt ayrımlara tâbidir?.....................35\n22. Niteliğine göre özel haklar nelerdir?.......................................................35\n23. Konularına göre özel haklar nelerdir?...................................................36\n24. Etkilerine göre özel haklar nelerdir?....................................................... 37\n25."}, {"page": 3, "chunk_index": 3, "text": "37\n25. Devrine göre özel haklar nelerdir?...........................................................38\n26. Bir hakkın sahibi ve süjesi kim olabilir? Sahipsiz hak olabilir mi?.39\n27. Gerçek ve tüzel kişi kimdir ve bunlar nasıl hak sahibidir?...............39\n28. Hak sahibi olan gerçek ve tüzel kişiler, haklarını nasıl\nkullanabilirler? Her hak sahibi hakkını doğrudan\nkullanabilir mi?.............................................................................................40\n29. Bir hak genel olarak nasıl kazanılır veya kaybedilir?.........................41"}, {"page": 4, "chunk_index": 0, "text": "XV\n30. Bir hakkın kazanılmasında ve kaybedilmesinde kişinin\niyiniyetli olması önem taşır mı?................................................................ 42\n31. Hakların kullanılması bakımından, genel bir sınırlama söz\nkonusu mudur?..............................................................................................43\n32. Dürüstlük kuralı nedir, iyiniyetten bir farkı var mıdır?....................43\n33. Hakkın kötüye kullanılması neyi ifade etmektedir?...........................44\n34. Kanuna karşı hile ve böyle bir davranışın sonucu nedir?.................46\n35. Ölçülülük (Oranlılık) İlkesi Nedir ve Hangi Hukukî\nSorunlarda/Konularda İşlev Görür?..................................................... 47\n§ 3. HUKUK KAVRAMI ILE İLGILI TEMEL BILGILER............51\n36."}, {"page": 4, "chunk_index": 1, "text": "HUKUK KAVRAMI ILE İLGILI TEMEL BILGILER............51\n36. Toplumsal düzen kuralları, sadece hukuk kurallarından mı\noluşur?.............................................................................................................. 51\n37. Toplumsal düzen kuralı olarak din kuralları nedir?.........................52\n38. Toplumsal düzen kuralı olarak ahlâk kuralları nedir?.....................52\n39. Toplumsal düzen kuralı olarak görgü kuralları nedir?.....................53\n40. Hukuk kurallarının diğer toplumsal düzen kurallarıyla\nbenzerlik ya da farklılığı nedir?................................................................53\n41. Hukuk tekil bir yapıyı mı ifade etmektedir; yoksa, hukuk da\nkendi içinde alt bölümlere ya da ayrımlara tâbi tutulabilir mi?....54\n42."}, {"page": 4, "chunk_index": 2, "text": "Hukuk tekil bir yapıyı mı ifade etmektedir; yoksa, hukuk da\nkendi içinde alt bölümlere ya da ayrımlara tâbi tutulabilir mi?....54\n42. Kamu hukuku – özel hukuk ayrımı neye dayanmaktadır ve\nbu alanlar neyi düzenlemektedir?...........................................................55\n43. Kamu hukukunun alt dalları nelerdir?..................................................56\n44. Özel hukukunun alt dalları nelerdir?.....................................................58\n45. Karma hukuk alanı denildiğinde ne anlaşılmaktadır?.....................60\n46. Maddî hukuk – şeklî hukuk ayrımı neyi ifade etmektedir ve\nbu ayrım neye göre yapılmaktadır?......................................................... 62\n47. Tüm ülkeler aynı hukuk anlayışına ve sistemine mi\nsahiptirler?"}, {"page": 4, "chunk_index": 3, "text": "Tüm ülkeler aynı hukuk anlayışına ve sistemine mi\nsahiptirler? Aynı değilse, farklı hukuk düzenlerinin ortak\nözellikleri mevcut mudur?..........................................................................63\n48. Farklı hukuk sistemleri nelerdir ve temel özellikleri nedir?.............63\n49. Uluslararası hukuk ve uluslarüstü hukuk neyi ifade etmektedir?.. 67\n50. Türk Hukuku hangi hukuk sistemi içinde yer almaktadır?.............68"}, {"page": 5, "chunk_index": 0, "text": "XVI\n51. Pozitif hukukun kaynakları nelerdir?....................................................69\n52. Yazılı kaynaklar nasıl kategorize edilebilir ve bunlar\narasında bir öncelik sırası var mıdır?..................................................... 70\n53. Yazılı hukuk kaynakları nelerdir ve hangi özellikleri\ntaşımaktadır?.................................................................................................74\n54. Yazılı olmayan hukuk kaynakları nelerdir?.........................................79\n55. İçtihat ya da içtihat hukuku neyi ifade etmektedir?...........................80\n56. Hukukun bu kaynakları arasında nasıl bir ilişki\nbulunmaktadır?.............................................................................................81\n§ 4."}, {"page": 5, "chunk_index": 1, "text": "Hukukun bu kaynakları arasında nasıl bir ilişki\nbulunmaktadır?.............................................................................................81\n§ 4. HUKUK KURALLARININ YAPISI - ÖZELLIKLERI\nVE ORTAYA ÇIKIŞI...................................................................83\n57. Hukuk kurallarının temel özellikleri nelerdir?....................................83\n58. Bir hukuk kuralının yapısı, unsurları nelerdir ve kural neleri\niçermektedir?..................................................................................................84\n59. Soyut ve genel bir hukuk kuralı, somut bir olaya nasıl\nuygulanmaktadır?........................................................................................85\n60."}, {"page": 5, "chunk_index": 2, "text": "Soyut ve genel bir hukuk kuralı, somut bir olaya nasıl\nuygulanmaktadır?........................................................................................85\n60. Hukuk kuralı tek tür müdür ya da hukuk kuralı amacı ve\nşekline göre farklılık gösterir mi?..............................................................86\n61. Kural koymanın ve kanun yapmanın bir tekniği var mıdır?...........88\n62. Kanunlaştırma ne demektir ve kanun yapmanın amacı nedir?.....88\n63. Bir kanunun ya da kanun hükmünün içeriği nasıl belirlenir,\nneye göre düzenlenir?...................................................................................89\n64."}, {"page": 5, "chunk_index": 3, "text": "Bir kanunun ya da kanun hükmünün içeriği nasıl belirlenir,\nneye göre düzenlenir?...................................................................................89\n64. Başarılı bir kanunlaştırma faaliyetinde nelere dikkat\nedilmelidir?.....................................................................................................90\n65. Bir kanunlaştırma süreci hangi aşamalardan geçerek\ngerçekleşir?......................................................................................................90\n§ 5. HUKUKUN UYGULANMASI..................................................93\n66. Hukukun uygulanmasından genel olarak ne anlaşılmalıdır?......... 93\n67. Hukukun yer bakımından uygulanması ne demektir?...................... 95\n68."}, {"page": 5, "chunk_index": 4, "text": "95\n68. Hukukun zaman bakımından uygulanması ne demektir?..............96\n69. Kanunlar ne zaman yürürlüğe girmiş sayılır ve uygulanabilir?.....97"}, {"page": 6, "chunk_index": 0, "text": "XVII\n70. Yürürlükte olan bir kanun ne zaman yürürlükten kalkmış\nkabul edilecektir?..........................................................................................98\n71. Bir kanun yürürlüğe girdiği tarihten itibaren gerçekleşen\nolaylara mı uygulanır, yoksa daha önceki olaylara da\nuygulanması mümkün müdür? Yani, kanunlar geriye yürür\nmü?..................................................................................................................100\n72. Aynı anda yürürlükte olan birden fazla hukuk kuralı aynı\nkonuyu düzenliyorsa, hangisi esas alınacaktır? Böyle bir\ndurumda yürürlük tarihinin önce veya sonra olması önemli\nmidir?.............................................................................................................102\n73."}, {"page": 6, "chunk_index": 1, "text": "Böyle bir\ndurumda yürürlük tarihinin önce veya sonra olması önemli\nmidir?.............................................................................................................102\n73. Hukukun anlam yönünden uygulanması ne demektir?..................104\n74. Temel yorum türleri nelerdir? Kuralı kimler anlam\nbakımından yorumlayabilir?..................................................................104\n75. Yorum yapılırken, kullanılacak temel yorum yöntemleri\nnelerdir?.........................................................................................................105\n76. Yorum yapılırken bu yöntemler yanında  hangi mantık\nkurallarına uyulmalıdır?..........................................................................108\n77."}, {"page": 6, "chunk_index": 2, "text": "Yorum yapılırken bu yöntemler yanında  hangi mantık\nkurallarına uyulmalıdır?..........................................................................108\n77. Yorumun önemi nedir ve nasıl yorum yapılmalıdır?........................114\n78. Eğer olaya uygulanacak bir kanun hükmü, bir kural\nyoksa bu durumda ne yapılacaktır? Böyle bir durumda\nuyuşmazlığın akıbeti ne olacaktır?.......................................................116\n79. Kanun koyucu bilinçli olarak bir boşluk bırakmışsa ya da\naçıkça hüküm olmasa dahi örtülü olarak kurala bir anlam\nverilebiliyorsa yine de boşluktan söz edilebilir mi?...........................117\n80."}, {"page": 6, "chunk_index": 3, "text": "Kanun koyucu bilinçli olarak bir boşluk bırakmışsa ya da\naçıkça hüküm olmasa dahi örtülü olarak kurala bir anlam\nverilebiliyorsa yine de boşluktan söz edilebilir mi?...........................117\n80. Bir boşluk söz konusu ise, ne yapılmalıdır, nasıl karar\nverilmelidir?.................................................................................................119\n81. Hâkimin hukuk yaratması ile takdir yetkisini kullanması\naynı şey midir?.............................................................................................120\n82. Hâkime takdir yetkisi tanınan hallerde, hâkim bu yetkiyi\nnasıl kullanmalıdır?...................................................................................121\n§ 6. HUKUKTA YAPTIRIM VE HAKLARIN KORUNMASI.....123\n83."}, {"page": 6, "chunk_index": 4, "text": "HUKUKTA YAPTIRIM VE HAKLARIN KORUNMASI.....123\n83. Hukukta çok önemli olan yaptırım kavramından ne\nanlamak gerekir?........................................................................................123"}, {"page": 7, "chunk_index": 0, "text": "XVIII\n84. Yaptırımın amacı ya da işlevi nedir?....................................................123\n85. Yaptırım türleri nelerdir, aralarında nasıl bir ilişki vardır?..........124\n86. Ceza yaptırımı nedir?...............................................................................124\n87. Tazminat yaptırımı nedir?......................................................................125\n88. Aynen teslim ve aynen ifa nasıl bir yaptırımdır?...............................126\n89. Bir yaptırım olarak hukuka aykırılığın ortadan kaldırılması\nveya önlenmesi nasıl gerçekleşir?............................................................127\n90. Yaptırım olarak “geçersizlik” denildiğinde ne anlamak\ngerekir ve geçersizlik tek tip midir?........................................................127\n91."}, {"page": 7, "chunk_index": 1, "text": "Yaptırım olarak “geçersizlik” denildiğinde ne anlamak\ngerekir ve geçersizlik tek tip midir?........................................................127\n91. Yaptırım olarak hak kaybı ne anlama gelmektedir?........................130\n92. Yaptırımların uygulanmasında ve hakların ihlâl edilmesi\ndurumunda, hakların korunması nasıl gerçekleşmektedir?..........131\n93. Hakların doğrudan hak sahibi eliyle korunması hangi\ndurumlarda söz konusu olur?.................................................................131\n94. Meşru müdafaa nedir ve hangi sınırlar içinde mümkündür?........132\n95. Zorunluluk (ızdırar) hâli hangi durumlarda söz konusudur?.....132\n96."}, {"page": 7, "chunk_index": 2, "text": "Zorunluluk (ızdırar) hâli hangi durumlarda söz konusudur?.....132\n96. Kuvvet kullanılarak hakkın korunması hangi şartlarda söz\nkonusudur?...................................................................................................133\n97. Hakkın asıl koruma şekli olan kamu eliyle, devlet gücüyle\nkoruma nasıl gerçekleşmektedir?...........................................................134\n98. Bu iki yol dışında (yani sahibi eliyle korunması ya da devlet\norganlarınca korunması), hakkın korunması bakımından\nbaşka yollar var mıdır?.............................................................................136\n99."}, {"page": 7, "chunk_index": 3, "text": "Bu iki yol dışında (yani sahibi eliyle korunması ya da devlet\norganlarınca korunması), hakkın korunması bakımından\nbaşka yollar var mıdır?.............................................................................136\n99. Hakkın korunması yöntemlerini karşılaştırdığımızda,\naralarındaki ilişkiyi nasıl açıklayabiliriz ve hakkın\nkorunması için nasıl bir yol izlenmesi uygundur?.............................136\n§ 7. UYUŞMAZLIK VE UYUŞMAZLIKLARIN ÇÖZÜMÜ........139\n100. Anlaşmazlık ya da uyuşmazlık nedir?.................................................139\n101. Uyuşmazlık çıkması durumunda, bunun giderilmesi için ne\nyapılmalıdır?................................................................................................139\n102."}, {"page": 7, "chunk_index": 4, "text": "Uyuşmazlık çıkması durumunda, bunun giderilmesi için ne\nyapılmalıdır?................................................................................................139\n102. Uyuşmazlıkları çözmek bakımından hangi yöntemler\nkullanılmaktadır?......................................................................................140"}, {"page": 8, "chunk_index": 0, "text": "XIX\n103. Uyuşmazlık çözüm yöntemleri bakımından bir\nderecelendirme yapmak mümkün müdür?.........................................142\n104. Yargılama yapılarak uyuşmazlığın çözümü ile yargılama\nyapmadan uyuşmazlığın çözümü arasındaki temel farklılık\nnedir?..............................................................................................................144\n105. Bu açıklamalar çerçevesinde, arabuluculuk ve uzlaştırmanın,\nsorun çözmedeki temel yaklaşımı nedir?.............................................144\n106. Alternatif uyuşmazlık çözüm yöntemlerinin yargısal çözüm\nyollarına göre yararları nelerdir?...........................................................145\n107."}, {"page": 8, "chunk_index": 1, "text": "Alternatif uyuşmazlık çözüm yöntemlerinin yargısal çözüm\nyollarına göre yararları nelerdir?...........................................................145\n107. Uyuşmazlıkları önlemek ve çözmek bakımından\nhukukçunun temel görevleri nelerdir?..................................................147\n108. Hakkı ihlâl edilen bir kimsenin hak arama özgürlüğü ve\nhukukî korunma talebi neyi ifade etmektedir?..................................148\n109. Hak arama sonunda kişinin elde edeceği koruma nasıl\nbir koruma olacaktır? Hakkın acilen korunması gereken\ndurumlarda kişilere sunulan farklı hukukî imkânlar var mıdır?.151\n110. Devlet hak dağıtımından kaçınabilir mi veya hak arama\nözgürlüğünü ortadan kaldırmak mümkün müdür?........................152\n§ 8."}, {"page": 8, "chunk_index": 2, "text": "Devlet hak dağıtımından kaçınabilir mi veya hak arama\nözgürlüğünü ortadan kaldırmak mümkün müdür?........................152\n§ 8. YARGI VE HUKUKÎ KORUMA TÜRLERI...........................155\n111. Türk yargı teşkilâtının temel yapılanması nasıldır?.........................155\n112. Bu yargı kolları arasında bir hiyerarşi veya üstünlük var mıdır?.156\n113. Adlî yargının konusunu neler oluşturmaktadır?...............................158\n114. Bu yargı kollarındaki mahkeme (yargı) teşkilâtını\ninceleyecek olursak, öncelikle adlî yargı kolu içinde medenî\nyargı bakımından mahkeme teşkilâtı nasıldır?.................................158\n115. Adlî yargının diğer bir alt dalı olan ceza yargısındaki\nmahkeme teşkilâtı nasıldır?.....................................................................166\n116."}, {"page": 8, "chunk_index": 3, "text": "Adlî yargının diğer bir alt dalı olan ceza yargısındaki\nmahkeme teşkilâtı nasıldır?.....................................................................166\n116. Ayrı bir yargı kolu olarak idarî yargının konusunu neler\noluşturmaktadır?........................................................................................170\n117. İdarî yargı teşkilâtı nasıl bir yapılanmaya sahiptir?.........................171\n118. Anayasa yargısının işlevi nedir ve nasıl yapılanmıştır?...................174\n119. Yargı ve hukukî koruma türleri neye göre ayrılmaktadır ve bu\nkonuda temel ölçü nedir?..........................................................................175"}, {"page": 9, "chunk_index": 0, "text": "XX\n120. Nihaî ve geçici hukukî koruma ne anlama gelmektedir?................175\n121. Medenî yargıda nihaî hukukî koruma nasıl gerçekleşmektedir?..176\n122. Medenî yargıda geçici hukukî koruma nasıl gerçekleşmektedir?..179\n123. Ceza yargısında nihaî hukukî koruma nasıl gerçekleşmektedir?.181\n124. Ceza Yargısında geçici hukukî korumalar (koruma\ntedbirleri) nasıl gerçekleşmektedir?.......................................................182\n125. Anayasa yargısında nihaî hukukî koruma nasıl\ngerçekleşmektedir?......................................................................................183\n126. Anayasa yargısında geçici hukukî koruma (yürürlüğün\ndurdurulması) nasıl gerçekleşmektedir?..............................................185\n127."}, {"page": 9, "chunk_index": 1, "text": "Anayasa yargısında geçici hukukî koruma (yürürlüğün\ndurdurulması) nasıl gerçekleşmektedir?..............................................185\n127. İdarî yargıda nihaî hukukî koruma nasıl gerçekleşmektedir?.......186\n128. İdarî yargıda geçici hukukî koruma (yürütmenin\ndurdurulması) nasıl gerçekleşmektedir?..............................................186\n129. Değişik yargı alanlarındaki yargılama faaliyetleri\nkarşılaştırıldığında bunlar arasındaki benzerlik ve farklar\niçin ne söylenebilir?.....................................................................................187\n§ 9. BAZI ÖNEMLI KAVRAM VE KURUMLAR.........................191\n130. Hukuktaki temel kavram ve kurumları açıklamak üzere ve\nonlara temel teşkil edecek bir sistemden bahsedilebilir mi?...........191\n131."}, {"page": 9, "chunk_index": 2, "text": "Hukuktaki temel kavram ve kurumları açıklamak üzere ve\nonlara temel teşkil edecek bir sistemden bahsedilebilir mi?...........191\n131. Hukukun temel kavramlarını sırasıyla tanımlamaya\nbaşlarsak, “hukukî olay” nedir?.............................................................193\n132. “Hukukî fiil” ne demektir?.......................................................................193\n133. “Hukukî işlem” neyi ifade etmektedir?.................................................194\n134. İrade beyanının sayısına göre hukukî işlemler nasıl\nsınıflandırılmaktadır?..............................................................................196\n135. Etkileri bakımından hukukî işlemler nasıl\nsınıflandırılmaktadır?..............................................................................198\n136."}, {"page": 9, "chunk_index": 3, "text": "Etkileri bakımından hukukî işlemler nasıl\nsınıflandırılmaktadır?..............................................................................198\n136. Yasama işlemi nasıl bir hukukî işlemdir?............................................198\n137. İdarî işlem nasıl bir hukukî işlemdir?....................................................199\n138. İdarî işlemleri gerçekleştiren idare nasıl bir yapılanmaya ve\nteşkilâta sahiptir?.......................................................................................200\n139. Usûlî işlemler nasıl hukukî işlemlerdir?................................................202"}, {"page": 10, "chunk_index": 0, "text": "XXI\n140. Kişiliği ilgilendiren işlemler nasıl hukukî işlemlerdir?.....................203\n141. Malvarlığını ilgilendiren işlemler nasıl hukukî işlemlerdir?...........204\n142. Hüküm ifade edeceği an bakımından hukukî işlemler nasıl\nsınıflandırılmaktadır?..............................................................................206\n143. Oldukça geniş bir uygulama alanı olan, “borç”, “borç ilişkisi”\nne anlama gelmektedir?............................................................................207\n144. Borç ilişkisi nasıl bir sorumluluk doğurmaktadır?...........................208\n145. Borç ilişkisinin (borcun) kaynağı ya da kaynakları nedir?............209\n146. Borç kaynağı olarak sözleşme nedir?....................................................209\n147."}, {"page": 10, "chunk_index": 1, "text": "Borç kaynağı olarak sözleşme nedir?....................................................209\n147. Borç kaynağı olarak haksız fiil nedir?...................................................210\n148. Borç kaynağı olarak sebepsiz zenginleşme nedir?.............................212\n149. Sorumluluk bakımından önem taşıyan kusur neyi ifade\netmektedir?...................................................................................................213\n150. Hukukun konusu olarak eşya nedir ve hukuk bakımından\nneden önemlidir?.........................................................................................215\n151. Eşya ile ilgili olarak aynî hak ne demektir?.........................................215\n152."}, {"page": 10, "chunk_index": 2, "text": "Eşya ile ilgili olarak aynî hak ne demektir?.........................................215\n152. Bir şey üzerinde sadece fiilî hâkimiyeti bulunup da tam\nolarak hak sahibi olmamak mümkün müdür?..................................216\n153. Bir hakkın güvence (teminat) altına alınması ne anlama\ngelmektedir?.................................................................................................217\n154. Hukukta pek çok hakkın kullanımı sürelere bağlanmıştır; bu\nçerçevede hukukta süre denildiğinde ne anlaşılmaktadır?.............218\n155. Ceza hukukuna hâkim olan genel ilkeler nelerdir?...........................220\n156. Yargılama hukukunda göz önünde bulundurulması gereken\ntemel ilkeler nelerdir?................................................................................222\n157."}, {"page": 10, "chunk_index": 3, "text": "Yargılama hukukunda göz önünde bulundurulması gereken\ntemel ilkeler nelerdir?................................................................................222\n157. İspat ve delil ne demektir, önemi nedir?................................................223\n158. Birçok yönden önemli olan belge ne demektir? Senetle belge\naynı şey midir?.............................................................................................225\n159. Belge ve senedin ispat gücü, diğer delillerden farklı mıdır?.............227\n160. Senet türleri nelerdir?.................................................................................228\n161. Borç senedi ne demektir?...........................................................................229\n162."}, {"page": 10, "chunk_index": 4, "text": "Borç senedi ne demektir?...........................................................................229\n162. Kıymetli evrak nedir?.................................................................................229"}, {"page": 11, "chunk_index": 0, "text": "XXII\n163. Tacir kimdir?................................................................................................231\n§ 10. HUKUKTA METOD............................................................... 233\n164. Hukukta metoddan söz edildiğine göre, hukuk gerçekten\nbilim midir?..................................................................................................233\n165. Hukukî bir sorunun çözümünde izlenmesi gereken yöntem ve\ndikkat edilmesi gereken hususlar nelerdir?.........................................234\n166. Hukukî bir araştırmada ve yazmada nelere dikkat\nedilmelidir? Bu konuda hareket noktası ne olmalıdır?...................236\n167."}, {"page": 11, "chunk_index": 1, "text": "Bu konuda hareket noktası ne olmalıdır?...................236\n167. Hukukî bir metinde ön hazırlık veya araştırma genel olarak\nnasıl yapılmalıdır?.....................................................................................236\n168. Somut olarak bir dilekçe yazarken temel olarak nelere dikkat\nedilmelidir?...................................................................................................237\n169. Yargı organlarına verilecek dilekçeler, normal bir dilekçeye\ngöre farklılık göstermekte midir?............................................................238\n170. Bir mahkeme kararının yazımında temel olarak nelere\ndikkat edilmelidir?.....................................................................................239\n171."}, {"page": 11, "chunk_index": 2, "text": "Bir mahkeme kararının yazımında temel olarak nelere\ndikkat edilmelidir?.....................................................................................239\n171. Bir hukukî bilimsel çalışmanın yazımında temel olarak\nnelere dikkat edilmelidir?.........................................................................240\n172. Yazım dışında, özellikle hukukta sözlü ifadenin ve anlatımın\nönemi nedir?.................................................................................................241\n173. Sözlü ifadede dikkate edilmesi gereken temel noktalar nelerdir?..242\n174. Hukukla mantık arasında nasıl bir ilişki vardır?..............................245\n175. Hukuk ve matematik arasında nasıl bir ilişki bulunmaktadır?....246\n§ 11. HUKUKÇU KIMLIĞI VE HUKUK ETIĞI..........................."}, {"page": 11, "chunk_index": 3, "text": "HUKUKÇU KIMLIĞI VE HUKUK ETIĞI........................... 249\n176. Hukuk fakültesi mezunu olmak, gerçekten hukukçu olmak\ndemek midir?...............................................................................................249\n177. Hukuk fakültesi mezunlarının temel meslek alanları nelerdir?....250\n178. Hukuk eğitiminin temel aşamaları nelerdir?......................................251\n179. Hukuk ve hukukçu bakımından etik değerler neden önemlidir?...253\n180. Hukukçunun toplum içindeki görevi nedir?........................................256\n181. Hukukta bazı adlî geleneklerin bu etik değerlerle ilgisi var\nmıdır?.............................................................................................................257"}, {"page": 12, "chunk_index": 0, "text": "XXIII\n§ 12. PRATIK ÇALIŞMALAR VE UYGULAMALAR...................259\nI. ÇÖZÜMÜ VERİLMİŞ OLAN PRATİK\nÇALIŞMALAR..............................................................259\nII. ÇÖZÜMÜ VERİLMEMİŞ OLAN PRATİK\nÇALIŞMALAR............................................................. 280\nIII. TEST SORULARI.........................................................315\n§ 13. SEÇİLMİŞ LATİNCE HUKUK İLKELERİ VE\nKURALLARI............................................................................ 363\nI. ADALET/ADALETSİZLİK......................................... 363\nII. HAKKANİYET............................................................ 364\nIII. HUKUK.........................................................................365\nIV. HUKUK KURALLARI, KANUNLAR....................... 366\nV."}, {"page": 12, "chunk_index": 1, "text": "366\nV. MAHKEMELER/HÂKİMLER...................................367\nVI. HUKUK KURALLARININ YORUMLANMASI...... 368\nVII. MAHKEME KARARLARI, KESİN HÜKÜM\nETKİSİ...........................................................................370\nVIII. AVUKATLAR................................................................370\nIX. HUKUKÎ İŞLEMLER, SÖZLEŞMELER.....................371\nX. İSPAT.............................................................................372\nXI. SUÇ VE CEZA...............................................................372\nXII. MUHTELİF...................................................................372"}, {"page": 14, "chunk_index": 0, "text": "KONULARIN SİSTEMATİK PLANI\nGİRİŞ\nI. Hukuk Başlangıcı ve Hukuka Giriş Derslerinin Temel Amacı\nA. Hukuk Fakültesi Öğrencileri İçin\nB. Hukuk Eğitimi Dışında Eğitim Alan veya Bilgi Edinmek İste-\nyenler İçin\nII. İyi Bir Hukukçu Olmak İçin Başlangıçta Dikkat Edilmesi\nGereken Hususlar\nIII. İyi Bir Hukukçu Olmanın Temel Formülü\nIV. Hukuk Başlangıcı Dersinde İzlenecek Yöntem\n§ 1. HUKUKUN TEMEL KAVRAMLARI\nI. Hak\nA. Hak Kavramı\nB. Hak Sahipliği\nC. Hakkı Açıklayan Farklı Görüşler\n1. İrade Teorisi\n2. Menfaat Teorisi\n3. Karma Teori\n4. Hakkı Reddeden Anlayış\nD. Hak ve Ödev Arasındaki İlişki\nII. Hukuk"}, {"page": 15, "chunk_index": 0, "text": "XXVI\nA. Hukuk Kavramı\nB. Hukukun Temel Amaçları\n1. Genel Olarak\n2. Toplum Yaşamını Düzenleme (Şeklî Amaç)\n3. İhtiyaçları Karşılama (Maddî Amaç)\n4. Adaleti Gerçekleştirme (Etik Amaç)\nC. Hukukun Temeli Hakkında Görüşler\n1. Hukuku İrade Ürünü Sayan Görüşler\na. Tanrısal İrade Teorisi\nb. Kişisel İrade Teorisi\nc. Genel İrade Teorisi\n2. Hukuku İrade Dışı Sayan Görüşler\n3. Pozitivist Görüşler\nD. Hukukun Değişik Anlamları\n1. Pozitif Hukuk\n2. Doğal (İdeal) Hukuk\n3. Objektif-Sübjektif Hukuk\n4. Evrensel-Yerel Hukuk\n5. Hukukî Pozitivizm-Doğal Hukuk İlişkisi\nIII. Adalet\nA. Adalet Kavramı\nB. Adalet Kavramının İçeriği\nC. Dağıtıcı ve Denkleştirici Adalet\nD. Adalet ve Eşitlik Arasındaki İlişki\nE. Hak, Hukuk ve Adalet Arasındaki İlişki\n§ 2. HAK\nI. Hakkın Türleri\nA. Genel Olarak\nB. Kamu Hakları"}, {"page": 16, "chunk_index": 0, "text": "XXVII\n1. Genel Nitelikli Kamu Hakları\n2. Özel Nitelikli Kamu Hakları\n3. Kamu Haklarına İlişkin Sınırlamalar\nC. Özel Haklar\n1. Nitelikleri Yönünden Haklar\na. Mutlak Haklar\nb. Nisbî Haklar\n2. Konuları Yönünden Haklar\na. Şahısvarlığı Hakları\nb. Malvarlığı Hakları\n3. Etkileri Yönünden Haklar\na. Yenilik Doğuran (İnşaî) Haklar\nb. Yenilik Doğurmayan Haklar\n4. Devri Yönünden Haklar\na. Kişiye Bağlı Haklar\nb. Kişiye Bağlı Olmayan Haklar\nII. Hakkın Süjesi\nA. Genel Olarak\nB. Gerçek Kişiler\nC. Tüzel Kişiler\nIII. Hakların Kazanılması ve Kaybedilmesi\nA. Hakların Kazanılması\nB. Hakların Kaybedilmesi\nC. Hakların Kazanılmasında ve Kaybında İyiniyet\nIV. Hakların Kullanılması\nA. Hakkın Kullanılması\nB. Hakkın Kullanılması Bakımından Genel Sınırlar\n1. Genel Olarak\n2. Dürüstlük Kuralı"}, {"page": 17, "chunk_index": 0, "text": "XXVIII\n3. Hakkın Kötüye Kullanılması\n4. Kanuna Karşı Hile\n5. Ölçülülük İlkesi\n§ 3. HUKUK\nI. Hukuk Kuralları ve Diğer Toplumsal Düzen Kuralları\nA. Toplumsal Düzen Kuralları\nB. Din Kuralları\nC. Ahlâk Kuralları\nD. Görgü Kuralları\nE. Hukuk Kuralları ile Diğer Toplumsal Kuraların Karşılaştır-\nması\nII. Hukukun Dalları\nA. Genel Olarak\nB. Kamu Hukuku – Özel Hukuk\n1. Genel Olarak\n2. Kamu Hukuku Dalları\n3. Özel Hukuk Dalları\n4. Karma Hukuk Dalları\nC. Maddî Hukuk – Şeklî Hukuk\n1. Genel Olarak\n2. Maddî Hukuk Dalları\n3. Şeklî Hukuk Dalları\nIII. Hukuk Sistemleri\nA. Genel Olarak\nB. Roma Hukuku Sistemi\nC. Common Law (Anglo-Sakson) Sistemi\nD. İslam Hukuku Sistemi\nE. Sosyalist Hukuk Sistemi\nF. Uluslararası ve Ulusalüstü Hukuk Sistemleri"}, {"page": 18, "chunk_index": 0, "text": "XXIX\nG. Türk Hukuk Sisteminin Dünü ve Bugünü\nIV. Pozitif Hukukun Kaynakları\nA. Genel Olarak\nB. Yazılı Hukuk Kaynakları\n1. Anayasa\n2. Kanunlar\n3. Uluslararası Antlaşmalar\n4. Yürütmenin Yaptığı Norm Düzenlemeleri\na. Genel Olarak\nb. Eski ve Yeni Sistemin Karşılaştırması\nC. Yazılı Olmayan Hukuk Kaynakları (Örf ve Adet – Gelenek\nHukuku)\nD. İçtihat Hukuku\n1. Yargı İçtihatları\n2. Bilimsel İçtihatlar\nE. Hukukun Kaynakları Arasındaki İlişki\n§ 4. HUKUK KURALI\nI. Hukuk Kuralının Özelliği ve Yapısı\nA. Hukuk Kuralının Temel Özellikleri\n1. Hukuk Kuralları Soyuttur\n2. Hukuk Kuralları Geneldir\n3. Hukuk Kuralları Objektiflik\n4. Hukuk Kuralları Bağlayıcıdır (Yaptırıma Tâbidir)\nB. Hukuk Kuralının Yapısı\nC. Hukuk Kuralında Altlama Faaliyeti\nII. Hukuk Kurallarının Türleri\nA. Emredici Kurallar\nB."}, {"page": 18, "chunk_index": 1, "text": "Emredici Kurallar\nB. Tamamlayıcı Kurallar\nC. Yorumlayıcı Kurallar"}, {"page": 19, "chunk_index": 0, "text": "XXX\nD. Tanımlayıcı Kurallar\nIII. Kanun Yapma Tekniği\nA. Kanunlaştırmanın Anlamı ve Kanun Yapmanın Amacı\nB. Kanunun Maddî İçeriğinde Benimsenen Yöntem\n1. Somut Olay (Kazuistik) Yöntemi\n2. Soyut Kural (Genel) Yöntemi\nC. Kanunlaştırma Süreci\n1. Başarılı Bir Kanun Yapmada Gözetilecek Hususlar\n2. Kanunlaştırma Süreci\n§ 5. HUKUKUN UYGULANMASI\nI. Hukuk Uygulamasının Anlamı\nII. Hukukun Yer Yönünden Uygulanması\nIII. Hukukun Zaman Yönünden Uygulanması\nA. Genel Olarak\nB. Kuralın Yürürlüğe Girmesi\nC. Kuralın Yürürlükten Kalkması\nD. Kuralın Geriye Yürümesi\nE. Zaman Bakımından Hangi Kuralın Uygulanacağı Sorunu\nIV. Hukukun Anlam Yönünden Uygulanması (Yorum)\nA. Genel Olarak\nB. Yorum Türleri\n1. Yasama Yorumu\n2. Yargısal Yorumu\n3. Bilimsel Yorum\nC. Yorum Yöntemleri\n1. Söze Göre (Lafzî) Yorum\n2."}, {"page": 19, "chunk_index": 1, "text": "Söze Göre (Lafzî) Yorum\n2. Amaca Göre (Gaî-Teleolojik) Yorum\n3. Tarihî Yorum"}, {"page": 20, "chunk_index": 0, "text": "XXXI\n4. Sistematik Yorum\n5. Kavramcı Yorum\n6. Menfaatler Dengesine Dayanan Yorum\nD. Yorumda Dikkat Edilecek Hususlar\n1. Temel Mantık İlkelerinin Gözetilmesi\na. Kıyas (Benzerlik)\nb. Aksi İle Kanıt (Mefhumu Muhalif)\nc. Evleviyet\nd. Örnekseyici Sayımın Benzerler Arası İlişkisi\ne. Absurt İle Kanıt\n2. Diğer Bazı İlkelerinin Gözetilmesi\na. Genel Kuralın Genel Olarak Yorumlanması\nb. Kuralın Ayrım Yapmadığı Yerde Yorumlayanın da\nYapmaması\nc. İstisnaların Dar Yorumlanması\nd. Açık Kurallarda Diğer Yorum Kurallarına Başvurul-\nmaması\n3. Yorumun Önemi ve Yoruma İlişkin Sorunların Aşılması\nV. Boşluk Doldurma\nA. Boşluk Kavramı ve Türleri\n1. Boşluk Kavramı\n2. Boşluk Türleri\na. Bilinçli-Bilinçsiz Boşluk\nb. Açık-Örtülü Boşluk\nc. Gerçek-Gerçek Olmayan Boşluk\nB. Boşluğun Giderilmesi\nVI."}, {"page": 20, "chunk_index": 1, "text": "Boşluğun Giderilmesi\nVI. Hâkimin Takdir Yetkisi\nA. Hâkimin Takdir Yetkisini Kullanacağı Alan\nB. Hâkimin Takdir Yetkisini Kullanması"}, {"page": 21, "chunk_index": 0, "text": "XXXII\n§ 6. HUKUKTA YAPTIRIM VE HAKLARIN KORUNMASI\nI. Hukukta Yaptırım ve Yaptırım Türleri\nA. Yaptırım Kavramı\nB. Yaptırımın Amacı\n1. Önleyici İşlevi\n2. Düzeltici İşlevi\nC. Yaptırım Türleri\n1. Genel Olarak\n2. Ceza Yaptırımı\n3. Tazminat Yaptırımı\n4. Aynen Teslime ve Aynen İfa\n5. Hukuka Aykırılığın Ortadan Kaldırılması ve Önlenmesi\n6. Geçersizlik\na. Yokluk\nb. Kesin Geçersizlik (Mutlak Butlan)\nc. İptal Edilebilirlik (Nispî Butlan)\nd. Eksiklik\n7. Hak Kaybı\nII. Hakların Korunması\nA. Genel Olarak\nB. Hakkın Doğrudan Hak Sahibi Eliyle Korunması\n1. Genel Olarak\n2. Meşru Müdafaa\n3. Zorunluluk (Izdırar) Hâli\n4. Kuvvet Kullanarak Hakkı Koruma\nC. Hakkın Kamu Eliyle Korunması\nD. Hakkın Korunması Bakımından Diğer Yollar\nE. Hakkın Korunması Yöntemlerinin Karşılaştırması"}, {"page": 22, "chunk_index": 0, "text": "XXXIII\n§ 7. UYUŞMAZLIK-UYUŞMAZLIK ÇÖZÜMÜ VE HAK ARAMA\nI. Uyuşmazlık ve Uyuşmazlık Çözüm Yöntemleri\nA. Anlaşmazlık ve Uyuşmazlık Kavramları\nB. Uyuşmazlıkları Çözme Yöntemleri\n1. Genel Olarak\n2. Uyuşmazlıkları Çözmede Uygulanacak Temel Yöntemler\na. Barışçı Yöntemler\nb. Çatışmacı (Mücadeleci Yöntemler)\n3. Uyuşmazlık Çözme Yöntemleri Arasındaki İlişkisi\n4. Yargılama Yapılarak ve Yargılama Yapmadan Uyuşmazlığı\nÇözmek Arasındaki Fark\n5. Yargılama Dışı Uyuşmazlık Çözüm Yöntemlerinin Temel\nYaklaşımı ve Yararları\nC. Uyuşmazlıkların Çözümünde Hukukçunun Temel Görevi\nII. Hak Arama Özgürlüğü ve Hukukî Korunma Talebi\nA. Hak Arama Özgürlüğü ve Hukukî Korunma Talebinin Anla-\nmı\nB. Hak Arama Çerçevesinde Elde Edilecek Korumanın Niteliği\nC. Devletin Hak Arama Özgürlüğü Karşısındaki Yükümlülüğü\n§ 8."}, {"page": 22, "chunk_index": 1, "text": "Devletin Hak Arama Özgürlüğü Karşısındaki Yükümlülüğü\n§ 8. YARGI TEŞKİLATI VE YARGILAMA FAALİYETİ\nI. Yargı Teşkilatının Temel Yapısı\nII. Temel Yargı Türleri ve Özellikleri\nA. Adlî Yargı Teşkilatı\n1. Adlî Yargının Alanı\n2. Medenî Yargı (Hukuk Yargısı)\na. Yargıtay (Temyiz Mahkemesi)\nb. Bölge Adliye Mahkemeleri (İstinaf Mahkemeleri)\nc. İlk Derece Mahkemeleri\n3. Ceza Yargısı"}, {"page": 23, "chunk_index": 0, "text": "XXXIV\na. Yargıtay (Temyiz Mahkemesi)\nb. Bölge Adliye Mahkemeleri (İstinaf Mahkemeleri)\nc. İlk Derece Mahkemeleri\nB. İdarî Yargı Teşkilâtı\n1. İdarî Yargının Alanı\n2. Danıştay\n3. Bölge İdare Mahkemeleri\n4. İdare ve Vergi Mahkemeleri\nC. Anayasa Yargısı Teşkilâtı\nD. Uyuşmazlık Yargı Teşkilâtı\nIII. Yargı Alanlarına Göre Sağlanan Hukukî Koruma Türleri\nA. Genel Olarak Hukukî Korumanın Türleri\nB. Adlî Yargıda\n1. Medeni Yargı (Hukuk Yargısı)\na. Nihaî Hukukî Koruma\nb. Geçici Hukukî Koruma\n2. Ceza Yargısı\na. Nihaî Hukukî Koruma\nb. Geçici Hukukî Koruma\nC. İdarî Yargıda\n1. Nihaî Hukukî Koruma\n2. Geçici Hukukî Koruma\nD. Anayasa Yargısında\nE. Farklı Yargılama Faaliyetlerinin Karşılaştırması\n§ 9. BAZI ÖNEMLİ TEMEL KAVRAM VE KURUMLAR\nI. Temel Kavram ve Kurumların Önemi ve Aralarındaki İlişki\nII."}, {"page": 23, "chunk_index": 1, "text": "Temel Kavram ve Kurumların Önemi ve Aralarındaki İlişki\nII. Hukukî Olay\nIII. Hukukî Fiil"}, {"page": 24, "chunk_index": 0, "text": "XXXV\nIV. Hukukî İşlem\nA. Kavram\nB. Hukukî İşlemlerin Sınıflandırılması\n1. İrade Beyanının Sayısı Bakımından\na. Tek Taraflı İşlemler\nb. İki Taraflı İşlemler\nc. Kararlar\nd. Ortak İşlemler\n2. Etkileri (Konuları) Bakımından\na. Yasama İşlemleri\nb. Yürütme (İdarî) İşlemler\naa. İdarî İşlemin Anlamı ve Unsurları\nbb. İdarî İşlemi Gerçekleştiren İdarenin Genel Yapısı\nc. Usûlî İşlemler\nd. Kişiliği İlgilendiren İşlemler\ne. Malvarlığını İlgilendiren İşlemler\naa. Genel Olarak\nbb. Borçlandırıcı İşlemler\ncc. Tasarrufî İşlemler\ndd. Kazandırıcı İşlemler\n3. Hüküm İfade Edeceği An Bakımından\nV. Borç İlişkisi\nA. Borç ve Borç İlişkisi\nB. Borç İlişkisi ve Sorumluluk\nC. Borç İlişkisinin (Borcun) Kaynakları\n1. Genel Olarak\n2. Sözleşme\n3. Haksız Fiil\n4. Sebepsiz Zenginleşme"}, {"page": 25, "chunk_index": 0, "text": "XXXVI\nVI. Kusur\nVII. Eşya ve Aynî Haklar\nA. Genel Olarak\nB. Aynî Haklar\nC. Zilyetlik\nVIII. Teminat\nIX. Hukukta Süreler ve Önemi\nX. Ceza Hukukuna Hâkim Olan Genel İlkeler\nXI. Yargılama Hukukunda Genel ve Temel İlkeler\nXII. İspat ve Delil\nXIII. Belge ve Senet\nA. Belge ve Senet Kavramları\nB. Delil Olarak Belgenin Kullanılması\nC. Senet Türleri\nD. Borç Senedi\nE. Kıymetli Evrak\nXIV. Tacir\n§ 10. HUKUKTA METOD\nI. Hukukun Bilim Olup Olmadığı Sorunu\nII. Hukukî Bir Sorunun Çözümünde İzlenecek Yöntem\nIII. Hukukî Araştırma ve Yazmada Dikkat Edilecek Hususlar\nA. Genel Olarak\nB. Hukukî Bir Metni Yazmadan Önce Hazırlık ve Araştırma\nC. Önemli Bazı Hukukî Metinlerin Yazılmasında Dikkat Edile-\ncek Hususlar\n1. Resmî Makamlara Verilecek Dilekçelerin Yazılması\n2. Mahkemelere Verilecek Dilekçelerin Yazılması\n3."}, {"page": 25, "chunk_index": 1, "text": "Mahkemelere Verilecek Dilekçelerin Yazılması\n3. Mahkeme Kararlarının Yazımı"}, {"page": 26, "chunk_index": 0, "text": "XXXVII\nD. Hukukî Bir Araştırma Çalışmasının Yazımı\nIV. Hukukî Sorunun ve Bilginin Sözlü Aktarımı\nA. Genel Olarak Konunun Önemi\nB. Sözlü İfadede Dikkat Edilmesi Gereken Temel Noktalar\nC. Farklı Bakımlardan Sözlü İfade, Tartışma ve Müzakere\nV. Hukukla Mantık Arasındaki İlişki\nVI. Hukukla Matematik Arasındaki İlişki\n§ 11. HUKUKÇU KİMLİĞİ VE HUKUKTA ETİK\nI. Hukuk Fakültesi Mezunu ve Hukukçu Ayrımı\nII. Hukuk Fakültesi Mezunlarının Temel Meslek Alanları\nIII. Hukuk Eğitiminin Aşamaları ve Özellikleri\nIV. Hukuk ve Hukukçu Bakımından Etik Değerlerin Önemi\nV. Hukukçunun Toplum İçindeki Görevi ve Önemi\nVI. Hukukta Adlî Gelenekler ve Hukuk Etiği İle İlişkisi\n§ 12. PRATİK ÇALIŞMALAR VE UYGULAMALAR\nI. Çözümü Verilmiş Olan Pratik Çalışmalar\nII. Çözümü Verilmemiş Olan Pratik Çalışmalar\nIII."}, {"page": 26, "chunk_index": 1, "text": "Çözümü Verilmemiş Olan Pratik Çalışmalar\nIII. Test Soruları\n§ 13. SEÇİLMİŞ LATİNCE HUKUK İLKELERİ VE KURALLARI\nI. Adalet/Adaletsizlik\nII. Hakkaniyet\nIII. Hukuk\nIV. Hukuk Kuralları, Kanunlar\nV. Mahkemeler/Hâkimler\nVI. Hukuk Kurallarının Yorumlanması\nVII. Mahkeme Kararları, Kesin Hüküm Etkisi"}, {"page": 27, "chunk_index": 0, "text": "XXXVIII\nVIII. Avukatlar\nIX. Hukukî İşlemler, Sözleşmeler\nX. İspat\nXI. Suç Ve Ceza\nXII. Muhtelif"}]